llms_handler/__init__.py
llms_handler/llms_handler.py
llms_handler/__pycache__/__init__.cpython-310.pyc
llms_handler/__pycache__/llms_handler.cpython-310.pyc
llms_handler/llm/__init__.py
llms_handler/llm/llm_handler.py
llms_handler/llm/__pycache__/__init__.cpython-310.pyc
llms_handler/llm/kimi/__init__.py
llms_handler/llm/kimi/kimi.py
llms_handler/llm/kimi/kimi_files.py
llms_handler/llm/kimi/__pycache__/__init__.cpython-310.pyc
llms_handler/llm/kimi/__pycache__/kimi.cpython-310.pyc
llms_handler/llm/kimi/__pycache__/kimi_files.cpython-310.pyc
llms_combo-0.1.4.dist-info/LICENSE
llms_combo-0.1.4.dist-info/METADATA
llms_combo-0.1.4.dist-info/WHEEL
llms_combo-0.1.4.dist-info/top_level.txt
llms_combo-0.1.4.dist-info/RECORD
