Metadata-Version: 2.1
Name: llms-combo
Version: 0.1.4
Summary: A simple example package
Home-page: https://github.com/yourusername/my_package
Author: Jared Hao
Author-email: 9190632@qq.com
Classifier: Programming Language :: Python :: 3
Classifier: License :: OSI Approved :: MIT License
Classifier: Operating System :: OS Independent
Requires-Python: >=3.6
License-File: LICENSE
